iLibrary7/__init__.py
iLibrary7/piewithrise1.py
piroschockmanagelite-2.0.0.dist-info/METADATA
piroschockmanagelite-2.0.0.dist-info/WHEEL
piroschockmanagelite-2.0.0.dist-info/top_level.txt
piroschockmanagelite-2.0.0.dist-info/RECORD
