Metadata-Version: 2.1
Name: piroschockmanagelite
Version: 2.0.0
Summary: Улучшенная библиотека от Пирожок с Рисом! Написана на языке программирования Python!
Home-page: https://telegra.ph/Socialnye-Seti-Ot--Zeeby--Light-07-23
Author: piroschock8develop
Author-email: dizelano.53.usinger.917@internet.ru
Project-URL: Pie With Rise's Resources, https://telegra.ph/Socialnye-Seti-Ot--Zeeby--Light-07-23
Project-URL: GitHub, https://github.com/pirosukirilla591/piroschock-jifersing391
Requires-Python: >=3.8.9
Requires-Dist: florestdevinstruments
